pytmx/__init__.py
pytmx/class_type.py
pytmx/constants.py
pytmx/element.py
pytmx/group_layer.py
pytmx/image_layer.py
pytmx/layer.py
pytmx/map.py
pytmx/object.py
pytmx/object_group.py
pytmx/properties.py
pytmx/property.py
pytmx/pytmx.py
pytmx/tile_layer.py
pytmx/tileset.py
pytmx/util_pygame.py
pytmx/util_pygame_sdl2.py
pytmx/util_pyglet.py
pytmx/util_pysdl2.py
pytmx/utils.py
pytmx_ng-3.34.1.dist-info/licenses/LICENSE
pytmx_ng-3.34.1.dist-info/METADATA
pytmx_ng-3.34.1.dist-info/WHEEL
pytmx_ng-3.34.1.dist-info/top_level.txt
pytmx_ng-3.34.1.dist-info/RECORD
