Metadata-Version: 2.4
Name: pytmx-ng
Version: 3.34.1
Summary: Loads tiled tmx maps
Author-email: bitcraft <leif.theden@gmail.com>
Maintainer-email: Peter Nearing <me@peternearing.ca>
License: LGPL-3.0-or-later
Project-URL: Homepage, https://github.com/pnearing/pytmx-ng
Project-URL: Repository, https://github.com/pnearing/pytmx-ng
Project-URL: Issues, https://github.com/pnearing/pytmx-ng/issues
Classifier: Intended Audience :: Developers
Classifier: Development Status :: 5 - Production/Stable
Classifier: License :: OSI Approved :: GNU Lesser General Public License v3 (LGPLv3)
Classifier: Programming Language :: Python :: 3.9
Classifier: Programming Language :: Python :: 3.10
Classifier: Programming Language :: Python :: 3.11
Classifier: Programming Language :: Python :: 3.12
Classifier: Programming Language :: Python :: 3.13
Classifier: Topic :: Games/Entertainment
Classifier: Topic :: Multimedia :: Graphics
Classifier: Topic :: Software Development :: Libraries :: pygame
Requires-Python: >=3.9
License-File: LICENSE
Provides-Extra: pygame
Requires-Dist: pygame>=2.0.0; extra == "pygame"
Provides-Extra: pygame-ce
Requires-Dist: pygame-ce>=2.1.3; extra == "pygame-ce"
Dynamic: license-file
